datasource_api_client/__init__.py
datasource_api_client/api/__init__.py
datasource_api_client/api/datasource/__init__.py
datasource_api_client/api/datasource/get_datasource_by_name.py
datasource_api_client/api/proxy/__init__.py
datasource_api_client/api/proxy/get_key_url.py
datasource_api_client/api/proxy/list_keys.py
datasource_api_client/api/proxy/log_metric.py
datasource_api_client/client.py
datasource_api_client/errors.py
datasource_api_client/models/__init__.py
datasource_api_client/models/datasource_config.py
datasource_api_client/models/datasource_dto.py
datasource_api_client/models/datasource_dto_added_by.py
datasource_api_client/models/datasource_dto_auth_type.py
datasource_api_client/models/datasource_dto_data_source_type.py
datasource_api_client/models/datasource_dto_status.py
datasource_api_client/models/datasource_owner_info.py
datasource_api_client/models/error_response.py
datasource_api_client/models/key_request.py
datasource_api_client/models/list_request.py
datasource_api_client/models/log_metric_m.py
datasource_api_client/models/log_metric_t.py
datasource_api_client/models/proxy_error_response.py
datasource_api_client/types.py
domino_data/__init__.py
domino_data/_feature_store/__init__.py
domino_data/_feature_store/client.py
domino_data/_feature_store/exceptions.py
domino_data/_feature_store/git.py
domino_data/_feature_store/logging.py
domino_data/_feature_store/run.py
domino_data/_feature_store/sync.py
domino_data/auth.py
domino_data/configuration_gen.py
domino_data/data_sources.py
domino_data/datasets.py
domino_data/logging.py
domino_data/meta.py
domino_data/netapp_volumes.py
domino_data/py.typed
domino_data/training_sets/__init__.py
domino_data/training_sets/client.py
domino_data/training_sets/model.py
domino_data/transfer.py
domino_data/vectordb.py
feature_store_api_client/__init__.py
feature_store_api_client/api/__init__.py
feature_store_api_client/api/default/__init__.py
feature_store_api_client/api/default/get.py
dominodatalab_data-6.7.3.dist-info/LICENSE
dominodatalab_data-6.7.3.dist-info/METADATA
dominodatalab_data-6.7.3.dist-info/WHEEL
dominodatalab_data-6.7.3.dist-info/RECORD
