Metadata-Version: 2.3
Name: dominodatalab-data
Version: 6.7.3
Summary: Domino Data API for interacting with Domino Data features
License: Apache Software License 2.0
Author: Gabriel Haim
Author-email: gabriel.haim@dominodatalab.com
Requires-Python: >=3.9,<4.0
Classifier: Development Status :: 5 - Production/Stable
Classifier: Intended Audience :: Developers
Classifier: License :: OSI Approved :: Apache Software License
Classifier: License :: Other/Proprietary License
Classifier: Operating System :: OS Independent
Classifier: Programming Language :: Python :: 3
Classifier: Programming Language :: Python :: 3.9
Classifier: Programming Language :: Python :: 3.10
Classifier: Programming Language :: Python :: 3.11
Classifier: Programming Language :: Python :: 3.12
Classifier: Programming Language :: Python :: 3.13
Classifier: Topic :: Software Development :: Libraries :: Python Modules
Requires-Dist: attrs (>=20.1.0)
Requires-Dist: backoff (>=1.11.1)
Requires-Dist: bson (>=0.5.10,<0.6.0)
Requires-Dist: h11 (>=0.16.0)
Requires-Dist: httpx (>=0.24.0)
Requires-Dist: loguru (>=0.5.3,<0.6.0)
Requires-Dist: pandas (>=1.3.0)
Requires-Dist: pyarrow (>=15.0.2)
Requires-Dist: python-dateutil (>=2.8.0,<3.0.0)
Requires-Dist: setuptools (>=78.1.1)
Requires-Dist: urllib3 (>=1.26.19,<3)
Project-URL: Homepage, https://github.com/dominodatalab/domino-data
Project-URL: Repository, https://github.com/dominodatalab/domino-data
